{
    "key": "group_57e281587f1bb",
    "title": "Theme Settings",
    "fields": [
        {
            "key": "field_64343d2936efd",
            "label": "General",
            "name": "",
            "aria-label": "",
            "type": "tab",
            "instructions": "",
            "required": 0,
            "conditional_logic": 0,
            "wrapper": {
                "width": "",
                "class": "",
                "id": ""
            },
            "placement": "left",
            "endpoint": 0
        },
        {
            "key": "field_64343d3436efe",
            "label": "Show Breadcrumbs",
            "name": "show_breadcrumbs",
            "aria-label": "",
            "type": "true_false",
            "instructions": "",
            "required": 0,
            "conditional_logic": 0,
            "wrapper": {
                "width": "",
                "class": "",
                "id": ""
            },
            "message": "",
            "default_value": 0,
            "ui_on_text": "",
            "ui_off_text": "",
            "ui": 1
        },
        {
            "key": "field_643597d9e5885",
            "label": "Show Category Sidebar",
            "name": "show_category_sidebar",
            "aria-label": "",
            "type": "true_false",
            "instructions": "",
            "required": 0,
            "conditional_logic": 0,
            "wrapper": {
                "width": "",
                "class": "",
                "id": ""
            },
            "message": "",
            "default_value": 0,
            "ui_on_text": "",
            "ui_off_text": "",
            "ui": 1
        },
        {
            "key": "field_6436d5e14b326",
            "label": "Show Category Buttons",
            "name": "show_category_buttons",
            "aria-label": "",
            "type": "true_false",
            "instructions": "*single post",
            "required": 0,
            "conditional_logic": 0,
            "wrapper": {
                "width": "",
                "class": "",
                "id": ""
            },
            "message": "",
            "default_value": 0,
            "ui_on_text": "",
            "ui_off_text": "",
            "ui": 1
        },
        {
            "key": "field_64a2faed87488",
            "label": "WOW Animation Speed",
            "name": "wow_animation_speed",
            "aria-label": "",
            "type": "number",
            "instructions": "",
            "required": 0,
            "conditional_logic": 0,
            "wrapper": {
                "width": "20",
                "class": "",
                "id": ""
            },
            "default_value": "",
            "min": "",
            "max": "",
            "placeholder": "",
            "step": 10,
            "prepend": "",
            "append": "ms"
        },
        {
            "key": "field_64a3011ad784b",
            "label": "WOW Animation Offset",
            "name": "wow_animation_offset",
            "aria-label": "",
            "type": "number",
            "instructions": "",
            "required": 0,
            "conditional_logic": 0,
            "wrapper": {
                "width": "20",
                "class": "",
                "id": ""
            },
            "default_value": 0,
            "min": "",
            "max": "",
            "placeholder": "",
            "step": 10,
            "prepend": "",
            "append": "px"
        },
        {
            "key": "field_622cb48cfe216",
            "label": "API",
            "name": "",
            "aria-label": "",
            "type": "tab",
            "instructions": "",
            "required": 0,
            "conditional_logic": 0,
            "wrapper": {
                "width": "",
                "class": "",
                "id": ""
            },
            "placement": "left",
            "endpoint": 0
        },
        {
            "key": "field_622cb498fe217",
            "label": "Google Map API",
            "name": "google_map_api",
            "aria-label": "",
            "type": "text",
            "instructions": "",
            "required": 0,
            "conditional_logic": 0,
            "wrapper": {
                "width": "",
                "class": "",
                "id": ""
            },
            "default_value": "",
            "placeholder": "",
            "prepend": "",
            "append": "",
            "maxlength": ""
        },
        {
            "key": "field_5553329c95271",
            "label": "Social Networks",
            "name": "",
            "aria-label": "",
            "type": "tab",
            "instructions": "",
            "required": 0,
            "conditional_logic": 0,
            "wrapper": {
                "width": "",
                "class": "",
                "id": ""
            },
            "placement": "left",
            "endpoint": 0
        },
        {
            "key": "field_550fdf33dc121",
            "label": "Social Networks",
            "name": "social_networks_options",
            "aria-label": "",
            "type": "repeater",
            "instructions": "Please, select social networks you want to display and add a correct link.",
            "required": 0,
            "conditional_logic": 0,
            "wrapper": {
                "width": "",
                "class": "",
                "id": ""
            },
            "collapsed": "",
            "min": 0,
            "max": 0,
            "layout": "row",
            "button_label": "Add Social Network",
            "rows_per_page": 20,
            "sub_fields": [
                {
                    "key": "field_550fdf85dc122",
                    "label": "Network",
                    "name": "network",
                    "aria-label": "",
                    "type": "select",
                    "instructions": "Select social networks you want to display on your website:",
                    "required": 0,
                    "conditional_logic": 0,
                    "wrapper": {
                        "width": "15",
                        "class": "",
                        "id": ""
                    },
                    "choices": {
                        "fa-facebook": "Facebook",
                        "fa-twitter": "Twitter",
                        "fa-google-plus": "Google+",
                        "fa-linkedin": "Linkedin",
                        "fa-youtube": "YouTube",
                        "fa-vimeo-square": "Vimeo",
                        "fa-instagram": "Instagram",
                        "fa-pinterest-p": "Pinterest",
                        "fa-dribbble": "Dribbble",
                        "fa-yelp": "Yelp",
                        "fa-flickr": "Flickr",
                        "fa-vine": "Vine"
                    },
                    "default_value": false,
                    "allow_null": 0,
                    "multiple": 0,
                    "ui": 0,
                    "ajax": 0,
                    "return_format": "value",
                    "placeholder": "",
                    "parent_repeater": "field_550fdf33dc121"
                },
                {
                    "key": "field_550fdfb5dc123",
                    "label": "URL",
                    "name": "url",
                    "aria-label": "",
                    "type": "text",
                    "instructions": "Please paste in a correct link for social network you've selected.",
                    "required": 0,
                    "conditional_logic": 0,
                    "wrapper": {
                        "width": "81",
                        "class": "",
                        "id": ""
                    },
                    "default_value": "",
                    "placeholder": "http:\/\/www.network.com",
                    "prepend": "",
                    "append": "",
                    "maxlength": "",
                    "parent_repeater": "field_550fdf33dc121"
                }
            ]
        },
        {
            "key": "field_63c52b7445348",
            "label": "Affiliate Disclosure",
            "name": "",
            "aria-label": "",
            "type": "tab",
            "instructions": "",
            "required": 0,
            "conditional_logic": 0,
            "wrapper": {
                "width": "",
                "class": "",
                "id": ""
            },
            "placement": "left",
            "endpoint": 0
        },
        {
            "key": "field_63c52b8545349",
            "label": "",
            "name": "affiliate_disclosure",
            "aria-label": "",
            "type": "wysiwyg",
            "instructions": "",
            "required": 0,
            "conditional_logic": 0,
            "wrapper": {
                "width": "",
                "class": "",
                "id": ""
            },
            "default_value": "",
            "tabs": "all",
            "toolbar": "full",
            "media_upload": 0,
            "delay": 0
        }
    ],
    "location": [
        [
            {
                "param": "options_page",
                "operator": "==",
                "value": "theme-general-settings"
            }
        ]
    ],
    "menu_order": 0,
    "position": "normal",
    "style": "default",
    "label_placement": "top",
    "instruction_placement": "label",
    "hide_on_screen": "",
    "active": true,
    "description": "",
    "show_in_rest": 0,
    "modified": 1688404277
}